<?xml version="1.0" encoding="UTF-8"?><?xml-stylesheet type="text/xsl" href="xslt/class.xsl"?><class name="EventDispatcher" namespace="com.crackerbarrel.events" extends="Class" author="Christopher Swenson" version="0.0.1">	<description><![CDATA[An extendable object that fires custom events.]]></description>	<constructor>	<return type="Object"><![CDATA[a new EventDispatcher Object]]>	</return></constructor>	<property name="listeners" type="Array">		<![CDATA[Holds an array of event listeners]]>	</property>	<method name="addListener">	<description><![CDATA[Allows for event delegation.]]></description>	<return type="null">	</return></method>	<method name="removeListener">	<description><![CDATA[Allows for removal of event delegation.]]></description>	<return type="null">	</return></method>	<method name="dispatch">	<description><![CDATA[Dispatches / Fires an event for event delegation.]]></description>	<return type="null">	</return></method>	<method name="hasListener">	<description><![CDATA[Checks to see if the given listener exists.]]></description>	<param name="handler" type="Function">		<![CDATA[The function to check for.]]>	</param>	<param name="context" type="Object=this">		<![CDATA[the object to use as the context of the method]]>	</param>	<return type="Boolean">	</return></method></class>